mysql_autoxtrabackup/__init__.py
mysql_autoxtrabackup/autoxtrabackup.py
mysql_autoxtrabackup/api/__init__.py
mysql_autoxtrabackup/api/main.py
mysql_autoxtrabackup/api/controller/__init__.py
mysql_autoxtrabackup/api/controller/controller.py
mysql_autoxtrabackup/backup_backup/__init__.py
mysql_autoxtrabackup/backup_backup/backup_archive.py
mysql_autoxtrabackup/backup_backup/backup_builder.py
mysql_autoxtrabackup/backup_backup/backuper.py
mysql_autoxtrabackup/backup_prepare/__init__.py
mysql_autoxtrabackup/backup_prepare/copy_back.py
mysql_autoxtrabackup/backup_prepare/prepare.py
mysql_autoxtrabackup/backup_prepare/prepare_builder.py
mysql_autoxtrabackup/general_conf/__init__.py
mysql_autoxtrabackup/general_conf/check_env.py
mysql_autoxtrabackup/general_conf/generalops.py
mysql_autoxtrabackup/general_conf/generate_default_conf.py
mysql_autoxtrabackup/general_conf/path_config.py
mysql_autoxtrabackup/process_runner/__init__.py
mysql_autoxtrabackup/process_runner/errors.py
mysql_autoxtrabackup/process_runner/process_runner.py
mysql_autoxtrabackup/utils/__init__.py
mysql_autoxtrabackup/utils/helpers.py
mysql_autoxtrabackup/utils/mysql_cli.py
mysql_autoxtrabackup/utils/version.py
mysql_autoxtrabackup-2.0.2.dist-info/entry_points.txt
mysql_autoxtrabackup-2.0.2.dist-info/LICENSE
mysql_autoxtrabackup-2.0.2.dist-info/WHEEL
mysql_autoxtrabackup-2.0.2.dist-info/METADATA
mysql_autoxtrabackup-2.0.2.dist-info/RECORD
