Metadata-Version: 2.1
Name: mysql_autoxtrabackup
Version: 2.0.2
Summary: MySQL-AutoXtrabackup command-line tool, for automating tedious MySQL physical backups management
Home-page: https://github.com/ShahriyarR/MySQL-AutoXtraBackup
Author: Shahriyar(Shako) Rzayev
Author-email: rzayev.sehriyar@gmail.com
Requires-Python: >=3.6
Classifier: Intended Audience :: Information Technology
Classifier: Intended Audience :: System Administrators
Classifier: Operating System :: POSIX :: Linux
Classifier: Programming Language :: Python :: 3
Classifier: Programming Language :: Python
Classifier: Topic :: Internet
Classifier: Topic :: Software Development :: Libraries :: Application Frameworks
Classifier: Topic :: Software Development :: Libraries :: Python Modules
Classifier: Topic :: Software Development :: Libraries
Classifier: Topic :: Software Development
Classifier: Typing :: Typed
Classifier: Development Status :: 4 - Beta
Classifier: Environment :: Console
Classifier: Intended Audience :: Developers
Classifier: License :: OSI Approved :: MIT License
Classifier: Programming Language :: Python :: 3 :: Only
Classifier: Programming Language :: Python :: 3.6
Classifier: Programming Language :: Python :: 3.7
Classifier: Programming Language :: Python :: 3.8
Requires-Dist: click >=3.3
Requires-Dist: pid >=2.0
Requires-Dist: humanfriendly >=2.0
Requires-Dist: fastapi >= 0.63.0
Requires-Dist: uvicorn >= 0.13.4
Requires-Dist: click >=3.3 ; extra == "all"
Requires-Dist: pid >=2.0 ; extra == "all"
Requires-Dist: humanfriendly >=2.0 ; extra == "all"
Requires-Dist: sphinx ; extra == "all"
Requires-Dist: sphinx_rtd_theme ; extra == "all"
Requires-Dist: sphinx-autobuild ; extra == "all"
Requires-Dist: jinja2 >=2.11.3 ; extra == "all"
Requires-Dist: fastapi >= 0.63.0 ; extra == "all"
Requires-Dist: uvicorn >= 0.13.4 ; extra == "all"
Requires-Dist: click >=3.3 ; extra == "dev"
Requires-Dist: pid >=2.0 ; extra == "dev"
Requires-Dist: humanfriendly >=2.0 ; extra == "dev"
Requires-Dist: pytest ==5.4.3 ; extra == "dev"
Requires-Dist: pytest-cov ==2.10.0 ; extra == "dev"
Requires-Dist: mypy ==0.812 ; extra == "dev"
Requires-Dist: isort >=5.0.6,<6.0.0 ; extra == "dev"
Requires-Dist: flake8 >=3.8.3,<4.0.0 ; extra == "dev"
Requires-Dist: black ==20.8b1 ; extra == "dev"
Requires-Dist: fastapi >= 0.63.0 ; extra == "dev"
Requires-Dist: uvicorn >= 0.13.4 ; extra == "dev"
Requires-Dist: sphinx ; extra == "doc"
Requires-Dist: sphinx_rtd_theme ; extra == "doc"
Requires-Dist: sphinx-autobuild ; extra == "doc"
Requires-Dist: jinja2 >=2.11.3 ; extra == "doc"
Requires-Dist: pytest ==5.4.3 ; extra == "test"
Requires-Dist: pytest-cov ==2.10.0 ; extra == "test"
Requires-Dist: mypy ==0.812 ; extra == "test"
Requires-Dist: isort >=5.0.6,<6.0.0 ; extra == "test"
Requires-Dist: flake8 >=3.8.3,<4.0.0 ; extra == "test"
Requires-Dist: black ==20.8b1 ; extra == "test"
Project-URL: Documentation, https://autoxtrabackup.azepug.az/
Provides-Extra: all
Provides-Extra: dev
Provides-Extra: doc
Provides-Extra: test
